rsdfoq/__init__.py
rsdfoq/diagnostic_info.py
rsdfoq/exit_information.py
rsdfoq/model.py
rsdfoq/params.py
rsdfoq/solver.py
rsdfoq/trust_region.py
rsdfoq/util.py
rsdfoq-1.0.dist-info/licenses/LICENSE
rsdfoq-1.0.dist-info/METADATA
rsdfoq-1.0.dist-info/WHEEL
rsdfoq-1.0.dist-info/top_level.txt
rsdfoq-1.0.dist-info/RECORD
